odoo8_addon_geoengine_base_geolocalize-8.0.0.1.0.99.dev11-py2.7-nspkg.pth
odoo8_addon_geoengine_base_geolocalize-8.0.0.1.0.99.dev11.dist-info/top_level.txt
odoo8_addon_geoengine_base_geolocalize-8.0.0.1.0.99.dev11.dist-info/WHEEL
odoo8_addon_geoengine_base_geolocalize-8.0.0.1.0.99.dev11.dist-info/RECORD
odoo8_addon_geoengine_base_geolocalize-8.0.0.1.0.99.dev11.dist-info/metadata.json
odoo8_addon_geoengine_base_geolocalize-8.0.0.1.0.99.dev11.dist-info/DESCRIPTION.rst
odoo8_addon_geoengine_base_geolocalize-8.0.0.1.0.99.dev11.dist-info/METADATA
odoo8_addon_geoengine_base_geolocalize-8.0.0.1.0.99.dev11.dist-info/namespace_packages.txt
odoo_addons/geoengine_base_geolocalize/__openerp__.py
odoo_addons/geoengine_base_geolocalize/__init__.py
odoo_addons/geoengine_base_geolocalize/README.rst
odoo_addons/geoengine_base_geolocalize/models/res_partner.py
odoo_addons/geoengine_base_geolocalize/models/__init__.py
odoo_addons/geoengine_base_geolocalize/i18n/ja.po
odoo_addons/geoengine_base_geolocalize/i18n/lv.po
odoo_addons/geoengine_base_geolocalize/i18n/zh_CN.po
odoo_addons/geoengine_base_geolocalize/i18n/nb_NO.po
odoo_addons/geoengine_base_geolocalize/i18n/tr_TR.po
odoo_addons/geoengine_base_geolocalize/i18n/ru.po
odoo_addons/geoengine_base_geolocalize/i18n/pt.po
odoo_addons/geoengine_base_geolocalize/i18n/fr_CH.po
odoo_addons/geoengine_base_geolocalize/i18n/it.po
odoo_addons/geoengine_base_geolocalize/i18n/es.po
odoo_addons/geoengine_base_geolocalize/i18n/nl_BE.po
odoo_addons/geoengine_base_geolocalize/i18n/ar.po
odoo_addons/geoengine_base_geolocalize/i18n/lt.po
odoo_addons/geoengine_base_geolocalize/i18n/ro.po
odoo_addons/geoengine_base_geolocalize/i18n/tr.po
odoo_addons/geoengine_base_geolocalize/i18n/mk.po
odoo_addons/geoengine_base_geolocalize/i18n/hr.po
odoo_addons/geoengine_base_geolocalize/i18n/bg.po
odoo_addons/geoengine_base_geolocalize/i18n/es_EC.po
odoo_addons/geoengine_base_geolocalize/i18n/zh_TW.po
odoo_addons/geoengine_base_geolocalize/i18n/hu.po
odoo_addons/geoengine_base_geolocalize/i18n/fr_CA.po
odoo_addons/geoengine_base_geolocalize/i18n/gl.po
odoo_addons/geoengine_base_geolocalize/i18n/ca.po
odoo_addons/geoengine_base_geolocalize/i18n/es_CR.po
odoo_addons/geoengine_base_geolocalize/i18n/sl.po
odoo_addons/geoengine_base_geolocalize/i18n/sr@latin.po
odoo_addons/geoengine_base_geolocalize/i18n/th.po
odoo_addons/geoengine_base_geolocalize/i18n/cs.po
odoo_addons/geoengine_base_geolocalize/i18n/pt_PT.po
odoo_addons/geoengine_base_geolocalize/i18n/eu.po
