Metadata-Version: 2.0
Name: odoo8-addon-geoengine-base-geolocalize
Version: 8.0.0.1.0.99.dev11
Summary: Geospatial support for base_geolocalize
Home-page: http://www.acsone.eu
Author: ACSONE SA/NV, Odoo Community Association (OCA)
Author-email: support@odoo-community.org
License: AGPL-3
Platform: UNKNOWN
Requires-Dist: odoo (<9.0a,>=8.0a)
Requires-Dist: odoo8-addon-geoengine-partner
Requires-Dist: requests
Classifier: Programming Language :: Python :: 2.7
Classifier: Framework :: Odoo
Classifier: License :: OSI Approved :: GNU Affero General Public License v3
